custom_s3_utils/__init__.py
custom_s3_utils/s3_utils.py
custom_s3_utils-0.1.0.dist-info/LICENSE
custom_s3_utils-0.1.0.dist-info/METADATA
custom_s3_utils-0.1.0.dist-info/WHEEL
custom_s3_utils-0.1.0.dist-info/top_level.txt
custom_s3_utils-0.1.0.dist-info/RECORD
